MANIFEST.in
README.txt
plonetheme.gemstone-configure.zcml
setup.cfg
setup.py
docs/HISTORY.txt
docs/INSTALL.txt
docs/LICENSE.CC
docs/LICENSE.txt
plonetheme/__init__.py
plonetheme.gemstone.egg-info/PKG-INFO
plonetheme.gemstone.egg-info/SOURCES.txt
plonetheme.gemstone.egg-info/dependency_links.txt
plonetheme.gemstone.egg-info/entry_points.txt
plonetheme.gemstone.egg-info/namespace_packages.txt
plonetheme.gemstone.egg-info/not-zip-safe
plonetheme.gemstone.egg-info/paster_plugins.txt
plonetheme.gemstone.egg-info/requires.txt
plonetheme.gemstone.egg-info/top_level.txt
plonetheme/gemstone/__init__.py
plonetheme/gemstone/configure.zcml
plonetheme/gemstone/profiles.zcml
plonetheme/gemstone/setuphandlers.py
plonetheme/gemstone/skins.zcml
plonetheme/gemstone/tests.py
plonetheme/gemstone/version.txt
plonetheme/gemstone/profiles/default/metadata.xml
plonetheme/gemstone/profiles/default/plonetheme.gemstone_various.txt
plonetheme/gemstone/profiles/default/skins.xml
plonetheme/gemstone/skins/plonetheme_gemstone_custom_images/bg.gif
plonetheme/gemstone/skins/plonetheme_gemstone_custom_images/bg_inner.gif
plonetheme/gemstone/skins/plonetheme_gemstone_custom_images/bg_navitem.gif
plonetheme/gemstone/skins/plonetheme_gemstone_custom_images/bg_newsitem.png
plonetheme/gemstone/skins/plonetheme_gemstone_custom_images/bgdate.gif
plonetheme/gemstone/skins/plonetheme_gemstone_custom_images/bgsubtitle.gif
plonetheme/gemstone/skins/plonetheme_gemstone_custom_images/header.gif
plonetheme/gemstone/skins/plonetheme_gemstone_custom_images/li.gif
plonetheme/gemstone/skins/plonetheme_gemstone_custom_images/plone.png
plonetheme/gemstone/skins/plonetheme_gemstone_custom_images/somepicture.gif
plonetheme/gemstone/skins/plonetheme_gemstone_custom_images/top.gif
plonetheme/gemstone/skins/plonetheme_gemstone_custom_templates/main_template.pt
plonetheme/gemstone/skins/plonetheme_gemstone_styles/base_properties.props
plonetheme/gemstone/skins/plonetheme_gemstone_styles/ploneCustom.css.dtml