Metadata-Version: 1.0
Name: plonetheme.gemstone
Version: 0.1a
Summary: Arcsin's Gemstone web design for Plone4
Home-page: http://svn.plone.org/svn/collective/plonetheme.gemstone
Author: Jonathan Riboux
Author-email: jonathan.riboux@gmail.com
License: CC
Platform: UNKNOWN
Classifier: Framework :: Plone
Classifier: Programming Language :: Python
